  <interface name="org.sunspec.Model.711">
    <property type="q" name="Ena" access="readwrite"/>
    <property type="q" name="AdptCtlReq" access="readwrite"/>
    <property type="q" name="AdptCtlRslt" access="read"/>
    <property type="q" name="NCtl" access="read"/>
    <property type="u" name="RvrtTms" access="readwrite"/>
    <property type="u" name="RvrtRem" access="read"/>
    <property type="q" name="RvrtCtl" access="readwrite"/>
    <property type="n" name="Db_SF" access="read"/>
    <property type="n" name="K_SF" access="read"/>
    <property type="n" name="RspTms_SF" access="read"/>
    <property type="u" name="DERFreqDroop.Ctl.DbOf" access="readwrite"/>
    <property type="u" name="DERFreqDroop.Ctl.DbUf" access="readwrite"/>
    <property type="q" name="DERFreqDroop.Ctl.KOf" access="readwrite"/>
    <property type="q" name="DERFreqDroop.Ctl.KUf" access="readwrite"/>
    <property type="u" name="DERFreqDroop.Ctl.RspTms" access="readwrite"/>
    <property type="n" name="DERFreqDroop.Ctl.PMin" access="readwrite"/>
    <property type="q" name="DERFreqDroop.Ctl.ReadOnly" access="read"/>
  </interface>
